djangocms_headings/__init__.py
djangocms_headings/cms_plugins.py
djangocms_headings/models.py
djangocms_headings/migrations/0001_initial.py
djangocms_headings/migrations/__init__.py
djangocms_headings/templates/djangocms_headings/heading.html
djangocms_headings-1.0.1.dist-info/LICENSE
djangocms_headings-1.0.1.dist-info/METADATA
djangocms_headings-1.0.1.dist-info/WHEEL
djangocms_headings-1.0.1.dist-info/top_level.txt
djangocms_headings-1.0.1.dist-info/RECORD
