Metadata-Version: 2.1
Name: djangocms-headings
Version: 1.0.1
Summary: djangocms plugin that implements HTML headings
Home-page: https://github.com/selectnull/djangocms-headings
Author: Sasha Matijasic
Author-email: sasha@selectnull.com
License: MIT
Platform: UNKNOWN
Classifier: Development Status :: 5 - Production/Stable
Classifier: Environment :: Web Environment
Classifier: Framework :: Django
Classifier: Intended Audience :: Developers
Classifier: License :: OSI Approved :: MIT License
Classifier: Operating System :: OS Independent
Classifier: Programming Language :: Python
Classifier: Programming Language :: Python :: 3
Classifier: Programming Language :: Python :: 3.6
Classifier: Programming Language :: Python :: 3.7
Classifier: Programming Language :: Python :: 3.8
Classifier: Programming Language :: Python :: 3.9
Requires-Dist: django-cms (>=3.6)
